knowrithm_py/__init__.py
knowrithm_py/config/__init__.py
knowrithm_py/config/config.py
knowrithm_py/dataclass/__init__.py
knowrithm_py/dataclass/config.py
knowrithm_py/dataclass/error.py
knowrithm_py/dataclass/response.py
knowrithm_py/knowrithm/__init__.py
knowrithm_py/knowrithm/agent.py
knowrithm_py/knowrithm/client.py
knowrithm_py/knowrithm/company.py
knowrithm_py/knowrithm/conversation.py
knowrithm_py/models/__init__.py
knowrithm_py/models/agent.py
knowrithm_py/models/conversation.py
knowrithm_py/models/document.py
knowrithm_py/models/user.py
knowrithm_py/services/__init__.py
knowrithm_py/services/address.py
knowrithm_py/services/admin.py
knowrithm_py/services/agent.py
knowrithm_py/services/auth.py
knowrithm_py/services/company.py
knowrithm_py/services/conversation.py
knowrithm_py/services/dashboard.py
knowrithm_py/services/database.py
knowrithm_py/services/document.py
knowrithm_py/services/lead.py
knowrithm_py/services/settings.py
knowrithm_py/services/website.py
knowrithm_py-0.1.22.dist-info/licenses/LICENSE
knowrithm_py-0.1.22.dist-info/METADATA
knowrithm_py-0.1.22.dist-info/WHEEL
knowrithm_py-0.1.22.dist-info/top_level.txt
knowrithm_py-0.1.22.dist-info/RECORD
