Metadata-Version: 2.4
Name: knowrithm-py
Version: 0.1.22
Summary: Knowrithm Python SDK
Author-email: Steven Saad <stevensaad35@gmail.com>
Project-URL: Homepage, https://github.com/Knowrithm/knowrithm-py.git
Requires-Python: >=3.8
License-File: LICENSE
Requires-Dist: requests>=2.25.0
Dynamic: license-file
